lusid_notifications/__init__.py
lusid_notifications/api/__init__.py
lusid_notifications/api/application_metadata_api.py
lusid_notifications/api/deliveries_api.py
lusid_notifications/api/event_types_api.py
lusid_notifications/api/manual_event_api.py
lusid_notifications/api/notifications_api.py
lusid_notifications/api/subscriptions_api.py
lusid_notifications/api_client.py
lusid_notifications/api_response.py
lusid_notifications/configuration.py
lusid_notifications/exceptions.py
lusid_notifications/extensions/__init__.py
lusid_notifications/extensions/api_client.py
lusid_notifications/extensions/api_client_factory.py
lusid_notifications/extensions/api_configuration.py
lusid_notifications/extensions/configuration_loaders.py
lusid_notifications/extensions/configuration_options.py
lusid_notifications/extensions/file_access_token.py
lusid_notifications/extensions/proxy_config.py
lusid_notifications/extensions/refreshing_token.py
lusid_notifications/extensions/rest.py
lusid_notifications/extensions/retry.py
lusid_notifications/extensions/socket_keep_alive.py
lusid_notifications/extensions/tcp_keep_alive_connector.py
lusid_notifications/models/__init__.py
lusid_notifications/models/access_controlled_action.py
lusid_notifications/models/access_controlled_resource.py
lusid_notifications/models/action_id.py
lusid_notifications/models/amazon_sqs_notification_type.py
lusid_notifications/models/amazon_sqs_notification_type_response.py
lusid_notifications/models/amazon_sqs_principal_auth_notification_type.py
lusid_notifications/models/amazon_sqs_principal_auth_notification_type_response.py
lusid_notifications/models/attempt.py
lusid_notifications/models/attempt_status.py
lusid_notifications/models/azure_service_bus_notification_type.py
lusid_notifications/models/azure_service_bus_type_response.py
lusid_notifications/models/create_notification_request.py
lusid_notifications/models/create_subscription.py
lusid_notifications/models/delivery.py
lusid_notifications_sdk-2.3.1.dist-info/METADATA
lusid_notifications_sdk-2.3.1.dist-info/WHEEL
lusid_notifications_sdk-2.3.1.dist-info/RECORD
